rer.newsletter-1.3.1-py3.10-nspkg.pth
rer/newsletter/__init__.py
rer/newsletter/configure.zcml
rer/newsletter/interfaces.py
rer/newsletter/pyproject.toml
rer/newsletter/setuphandlers.py
rer/newsletter/testing.py
rer/newsletter/upgrades.py
rer/newsletter/upgrades.zcml
rer/newsletter/utils.py
rer/newsletter/vocabularies.py
rer/newsletter/adapter/__init__.py
rer/newsletter/adapter/configure.zcml
rer/newsletter/adapter/sender.py
rer/newsletter/adapter/subscriptions.py
rer/newsletter/behaviors/__init__.py
rer/newsletter/behaviors/configure.zcml
rer/newsletter/behaviors/ships.py
rer/newsletter/browser/__init__.py
rer/newsletter/browser/configure.zcml
rer/newsletter/browser/settings.py
rer/newsletter/browser/channel/__init__.py
rer/newsletter/browser/channel/add.py
rer/newsletter/browser/channel/channelhistory.py
rer/newsletter/browser/channel/channelview.py
rer/newsletter/browser/channel/channelviewlet.py
rer/newsletter/browser/channel/configure.zcml
rer/newsletter/browser/channel/deleteexpiredusers.py
rer/newsletter/browser/channel/manageusers.py
rer/newsletter/browser/channel/subscribe.py
rer/newsletter/browser/channel/unsubscribe.py
rer/newsletter/browser/channel/templates/channelhistoryview.pt
rer/newsletter/browser/channel/templates/channelview.pt
rer/newsletter/browser/channel/templates/channelviewlet.pt
rer/newsletter/browser/channel/templates/confirm_subscription.pt
rer/newsletter/browser/channel/templates/confirm_unsubscription.pt
rer/newsletter/browser/channel/templates/manageusers.pt
rer/newsletter/browser/channel/templates/subscribechannel.pt
rer/newsletter/browser/channel/templates/unsubscribechannel.pt
rer/newsletter/browser/channel/templates/mail_templates/active_user.pt
rer/newsletter/browser/channel/templates/mail_templates/active_user_confirm.pt
rer/newsletter/browser/channel/templates/mail_templates/asynch_send_fail.pt
rer/newsletter/browser/channel/templates/mail_templates/asynch_send_success.pt
rer.newsletter-1.3.1.dist-info/LICENSE.GPL
rer.newsletter-1.3.1.dist-info/LICENSE.rst
rer.newsletter-1.3.1.dist-info/METADATA
rer.newsletter-1.3.1.dist-info/WHEEL
rer.newsletter-1.3.1.dist-info/entry_points.txt
rer.newsletter-1.3.1.dist-info/namespace_packages.txt
rer.newsletter-1.3.1.dist-info/top_level.txt
rer.newsletter-1.3.1.dist-info/RECORD
