Metadata-Version: 2.1
Name: rer.newsletter
Version: 1.3.1
Summary: An add-on for Plone
Home-page: https://pypi.python.org/pypi/rer.newsletter
Author: Filippo Campi
Author-email: filippo.campi@redturtle.it
License: GPL version 2
Keywords: Python Plone
Classifier: Environment :: Web Environment
Classifier: Framework :: Plone
Classifier: Framework :: Plone :: 5.0
Classifier: Programming Language :: Python
Classifier: Programming Language :: Python :: 2.7
Classifier: Operating System :: OS Independent
Classifier: License :: OSI Approved :: GNU General Public License v2 (GPLv2)
License-File: LICENSE.GPL
License-File: LICENSE.rst
Requires-Dist: mailmanclient ==3.1
Requires-Dist: plone.api
Requires-Dist: plone.app.tiles
Requires-Dist: collective.honeypot
Requires-Dist: plone.restapi
Requires-Dist: premailer ==3.1.1
Requires-Dist: Products.GenericSetup >=1.8.2
Requires-Dist: setuptools
Requires-Dist: z3c.jbot
Provides-Extra: test
Requires-Dist: plone.app.testing ; extra == 'test'
Requires-Dist: plone.testing >=5.0.0 ; extra == 'test'
Requires-Dist: plone.app.contenttypes ; extra == 'test'
Requires-Dist: plone.app.robotframework[debug] ; extra == 'test'
